{
  "mappings": [
    {
      "source": "parser.mbty",
      "original_offset": 914,
      "generated_offset": 4849,
      "length": 1
    },
    {
      "source": "parser.mbty",
      "original_offset": 917,
      "generated_offset": 4858,
      "length": 1
    },
    {
      "source": "parser.mbty",
      "original_offset": 1300,
      "generated_offset": 5671,
      "length": 108
    },
    {
      "source": "parser.mbty",
      "original_offset": 1410,
      "generated_offset": 5787,
      "length": 60
    },
    {
      "source": "parser.mbty",
      "original_offset": 1472,
      "generated_offset": 5855,
      "length": 9
    },
    {
      "source": "parser.mbty",
      "original_offset": 1483,
      "generated_offset": 5872,
      "length": 27
    },
    {
      "source": "parser.mbty",
      "original_offset": 1512,
      "generated_offset": 5907,
      "length": 88
    },
    {
      "source": "parser.mbty",
      "original_offset": 1848,
      "generated_offset": 6225,
      "length": 1
    },
    {
      "source": "parser.mbty",
      "original_offset": 1851,
      "generated_offset": 6234,
      "length": 1
    },
    {
      "source": "parser.mbty",
      "original_offset": 1895,
      "generated_offset": 6420,
      "length": 4
    },
    {
      "source": "parser.mbty",
      "original_offset": 2449,
      "generated_offset": 6807,
      "length": 19
    },
    {
      "source": "parser.mbty",
      "original_offset": 2470,
      "generated_offset": 6834,
      "length": 7
    },
    {
      "source": "parser.mbty",
      "original_offset": 2479,
      "generated_offset": 6849,
      "length": 7
    },
    {
      "source": "parser.mbty",
      "original_offset": 2363,
      "generated_offset": 7171,
      "length": 19
    },
    {
      "source": "parser.mbty",
      "original_offset": 2384,
      "generated_offset": 7198,
      "length": 22
    },
    {
      "source": "parser.mbty",
      "original_offset": 2690,
      "generated_offset": 8232,
      "length": 81
    },
    {
      "source": "parser.mbty",
      "original_offset": 2773,
      "generated_offset": 8321,
      "length": 345
    },
    {
      "source": "parser.mbty",
      "original_offset": 3120,
      "generated_offset": 8674,
      "length": 15
    },
    {
      "source": "parser.mbty",
      "original_offset": 3137,
      "generated_offset": 8697,
      "length": 84
    },
    {
      "source": "parser.mbty",
      "original_offset": 3377,
      "generated_offset": 9251,
      "length": 19
    },
    {
      "source": "parser.mbty",
      "original_offset": 3398,
      "generated_offset": 9278,
      "length": 7
    },
    {
      "source": "parser.mbty",
      "original_offset": 3407,
      "generated_offset": 9293,
      "length": 7
    },
    {
      "source": "parser.mbty",
      "original_offset": 3624,
      "generated_offset": 9663,
      "length": 9
    },
    {
      "source": "parser.mbty",
      "original_offset": 3635,
      "generated_offset": 9680,
      "length": 13
    },
    {
      "source": "parser.mbty",
      "original_offset": 3650,
      "generated_offset": 9701,
      "length": 2
    },
    {
      "source": "parser.mbty",
      "original_offset": 3457,
      "generated_offset": 9965,
      "length": 23
    },
    {
      "source": "parser.mbty",
      "original_offset": 2011,
      "generated_offset": 10322,
      "length": 8
    },
    {
      "source": "parser.mbty",
      "original_offset": 2021,
      "generated_offset": 10338,
      "length": 1
    },
    {
      "source": "parser.mbty",
      "original_offset": 2024,
      "generated_offset": 10347,
      "length": 7
    },
    {
      "source": "parser.mbty",
      "original_offset": 2198,
      "generated_offset": 10696,
      "length": 25
    },
    {
      "source": "parser.mbty",
      "original_offset": 2225,
      "generated_offset": 10729,
      "length": 2
    },
    {
      "source": "parser.mbty",
      "original_offset": 2229,
      "generated_offset": 10739,
      "length": 7
    },
    {
      "source": "parser.mbty",
      "original_offset": 2074,
      "generated_offset": 10954,
      "length": 12
    },
    {
      "source": "parser.mbty",
      "original_offset": 1698,
      "generated_offset": 11197,
      "length": 1
    },
    {
      "source": "parser.mbty",
      "original_offset": 1701,
      "generated_offset": 11206,
      "length": 1
    },
    {
      "source": "parser.mbty",
      "original_offset": 1745,
      "generated_offset": 11393,
      "length": 4
    },
    {
      "source": "parser.mbty",
      "original_offset": 1152,
      "generated_offset": 11644,
      "length": 49
    },
    {
      "source": "parser.mbty",
      "original_offset": 1034,
      "generated_offset": 11960,
      "length": 1
    },
    {
      "source": "parser.mbty",
      "original_offset": 1037,
      "generated_offset": 11969,
      "length": 1
    },
    {
      "source": "parser.mbty",
      "original_offset": 3768,
      "generated_offset": 12238,
      "length": 1
    },
    {
      "source": "parser.mbty",
      "original_offset": 3771,
      "generated_offset": 12247,
      "length": 1
    },
    {
      "source": "parser.mbty",
      "original_offset": 3935,
      "generated_offset": 12590,
      "length": 20
    },
    {
      "source": "parser.mbty",
      "original_offset": 3957,
      "generated_offset": 12618,
      "length": 7
    },
    {
      "source": "parser.mbty",
      "original_offset": 3966,
      "generated_offset": 12633,
      "length": 2
    },
    {
      "source": "parser.mbty",
      "original_offset": 3888,
      "generated_offset": 12903,
      "length": 1
    },
    {
      "source": "parser.mbty",
      "original_offset": 3891,
      "generated_offset": 12912,
      "length": 1
    },
    {
      "source": "parser.mbty",
      "original_offset": 4131,
      "generated_offset": 13277,
      "length": 19
    },
    {
      "source": "parser.mbty",
      "original_offset": 4152,
      "generated_offset": 13304,
      "length": 7
    },
    {
      "source": "parser.mbty",
      "original_offset": 4161,
      "generated_offset": 13319,
      "length": 7
    },
    {
      "source": "parser.mbty",
      "original_offset": 4084,
      "generated_offset": 13594,
      "length": 1
    },
    {
      "source": "parser.mbty",
      "original_offset": 4087,
      "generated_offset": 13603,
      "length": 1
    },
    {
      "source": "parser.mbty",
      "original_offset": 4331,
      "generated_offset": 13968,
      "length": 19
    },
    {
      "source": "parser.mbty",
      "original_offset": 4352,
      "generated_offset": 13995,
      "length": 7
    },
    {
      "source": "parser.mbty",
      "original_offset": 4361,
      "generated_offset": 14010,
      "length": 7
    },
    {
      "source": "parser.mbty",
      "original_offset": 4284,
      "generated_offset": 14285,
      "length": 1
    },
    {
      "source": "parser.mbty",
      "original_offset": 4287,
      "generated_offset": 14294,
      "length": 1
    },
    {
      "source": "parser.mbty",
      "original_offset": 4918,
      "generated_offset": 15001,
      "length": 104
    },
    {
      "source": "parser.mbty",
      "original_offset": 5024,
      "generated_offset": 15113,
      "length": 34
    },
    {
      "source": "parser.mbty",
      "original_offset": 5060,
      "generated_offset": 15155,
      "length": 202
    },
    {
      "source": "parser.mbty",
      "original_offset": 4411,
      "generated_offset": 15625,
      "length": 1
    },
    {
      "source": "parser.mbty",
      "original_offset": 4414,
      "generated_offset": 15634,
      "length": 1
    },
    {
      "source": "parser.mbty",
      "original_offset": 4531,
      "generated_offset": 16341,
      "length": 104
    },
    {
      "source": "parser.mbty",
      "original_offset": 4637,
      "generated_offset": 16453,
      "length": 34
    },
    {
      "source": "parser.mbty",
      "original_offset": 4673,
      "generated_offset": 16495,
      "length": 202
    },
    {
      "source": "parser.mbty",
      "original_offset": 5425,
      "generated_offset": 16990,
      "length": 20
    },
    {
      "source": "parser.mbty",
      "original_offset": 5447,
      "generated_offset": 17018,
      "length": 7
    },
    {
      "source": "parser.mbty",
      "original_offset": 5497,
      "generated_offset": 17318,
      "length": 20
    },
    {
      "source": "parser.mbty",
      "original_offset": 5519,
      "generated_offset": 17346,
      "length": 7
    },
    {
      "source": "parser.mbty",
      "original_offset": 5569,
      "generated_offset": 17645,
      "length": 19
    },
    {
      "source": "parser.mbty",
      "original_offset": 5590,
      "generated_offset": 17672,
      "length": 7
    },
    {
      "source": "parser.mbty",
      "original_offset": 5378,
      "generated_offset": 17947,
      "length": 1
    },
    {
      "source": "parser.mbty",
      "original_offset": 5381,
      "generated_offset": 17956,
      "length": 1
    },
    {
      "source": "parser.mbty",
      "original_offset": 5713,
      "generated_offset": 18225,
      "length": 1
    },
    {
      "source": "parser.mbty",
      "original_offset": 5716,
      "generated_offset": 18234,
      "length": 1
    },
    {
      "source": "parser.mbty",
      "original_offset": 5760,
      "generated_offset": 18517,
      "length": 27
    },
    {
      "source": "parser.mbty",
      "original_offset": 5789,
      "generated_offset": 18552,
      "length": 2
    },
    {
      "source": "parser.mbty",
      "original_offset": 5834,
      "generated_offset": 18843,
      "length": 30
    },
    {
      "source": "parser.mbty",
      "original_offset": 5866,
      "generated_offset": 18881,
      "length": 11
    },
    {
      "source": "parser.mbty",
      "original_offset": 5920,
      "generated_offset": 19188,
      "length": 47
    },
    {
      "source": "parser.mbty",
      "original_offset": 5969,
      "generated_offset": 19243,
      "length": 3
    },
    {
      "source": "parser.mbty",
      "original_offset": 6015,
      "generated_offset": 19612,
      "length": 9
    },
    {
      "source": "parser.mbty",
      "original_offset": 6026,
      "generated_offset": 19629,
      "length": 109
    },
    {
      "source": "parser.mbty",
      "original_offset": 6178,
      "generated_offset": 19981,
      "length": 42
    },
    {
      "source": "parser.mbty",
      "original_offset": 6263,
      "generated_offset": 20244,
      "length": 20
    },
    {
      "source": "parser.mbty",
      "original_offset": 6386,
      "generated_offset": 20506,
      "length": 1
    },
    {
      "source": "parser.mbty",
      "original_offset": 6389,
      "generated_offset": 20515,
      "length": 1
    },
    {
      "source": "parser.mbty",
      "original_offset": 6433,
      "generated_offset": 20768,
      "length": 1
    },
    {
      "source": "parser.mbty",
      "original_offset": 6436,
      "generated_offset": 20777,
      "length": 11
    },
    {
      "source": "parser.mbty",
      "original_offset": 6598,
      "generated_offset": 21140,
      "length": 1
    },
    {
      "source": "parser.mbty",
      "original_offset": 6601,
      "generated_offset": 21149,
      "length": 3
    },
    {
      "source": "parser.mbty",
      "original_offset": 6606,
      "generated_offset": 21160,
      "length": 1
    },
    {
      "source": "parser.mbty",
      "original_offset": 6650,
      "generated_offset": 21403,
      "length": 1
    },
    {
      "source": "parser.mbty",
      "original_offset": 6653,
      "generated_offset": 21412,
      "length": 1
    },
    {
      "source": "parser.mbty",
      "original_offset": 6825,
      "generated_offset": 21711,
      "length": 17
    },
    {
      "source": "parser.mbty",
      "original_offset": 6844,
      "generated_offset": 21736,
      "length": 2
    },
    {
      "source": "parser.mbty",
      "original_offset": 6848,
      "generated_offset": 21746,
      "length": 1
    },
    {
      "source": "parser.mbty",
      "original_offset": 6757,
      "generated_offset": 22003,
      "length": 21
    },
    {
      "source": "parser.mbty",
      "original_offset": 6780,
      "generated_offset": 22032,
      "length": 2
    }
  ]
}